README.md
setup.py
datamodels/__init__.py
datamodels/apps.py
datamodels/models.py
datamodels/tests.py
datamodels/management/__init__.py
datamodels/management/commands/__init__.py
datamodels/management/commands/datamodels_check.py
datamodels/management/commands/datamodels_loaddata.py
datamodels/management/commands/datamodels_loaddata_default.py
datamodels/management/commands/datamodels_show_fixtures.py
datamodels/management/commands/datamodels_show_stale_objects.py
datamodels/services/__init__.py
datamodels/services/fixtures_parser.py
datamodels/services/stale_objects.py
django_data_models.egg-info/PKG-INFO
django_data_models.egg-info/SOURCES.txt
django_data_models.egg-info/dependency_links.txt
django_data_models.egg-info/requires.txt
django_data_models.egg-info/top_level.txt