Metadata-Version: 1.0
Name: django-data-models
Version: 0.0.39
Summary: Django's DataModels
Home-page: https://github.com/TriplePoint-Software/django-data-models
Author: Max Syabro
Author-email: maxim@syabro.com
License: Apache License, Version 2.0
Platform: UNKNOWN
